grokcore.rest-4.1-py3.8-nspkg.pth
grokcore/rest/__init__.py
grokcore/rest/components.py
grokcore/rest/configure.zcml
grokcore/rest/directive.py
grokcore/rest/ftesting.zcml
grokcore/rest/interfaces.py
grokcore/rest/meta.py
grokcore/rest/meta.zcml
grokcore/rest/publication.py
grokcore/rest/rest.py
grokcore/rest/testing.py
grokcore/rest/tests/__init__.py
grokcore/rest/tests/test_functional.py
grokcore/rest/tests/functional/__init__.py
grokcore/rest/tests/functional/rest/__init__.py
grokcore/rest/tests/functional/rest/localgrants.py
grokcore/rest/tests/functional/rest/rest.py
grokcore.rest-4.1.dist-info/LICENSE.txt
grokcore.rest-4.1.dist-info/METADATA
grokcore.rest-4.1.dist-info/WHEEL
grokcore.rest-4.1.dist-info/namespace_packages.txt
grokcore.rest-4.1.dist-info/top_level.txt
grokcore.rest-4.1.dist-info/RECORD
