Metadata-Version: 2.1
Name: grokcore.rest
Version: 4.1
Summary: REST View component for Grok.
Home-page: https://github.com/zopefoundation/grokcore.rest
Author: Grok Team
Author-email: zope-dev@zope.dev
License: ZPL 2.1
Download-URL: https://pypi.org/project/grokcore.rest/
Platform: UNKNOWN
Classifier: Development Status :: 7 - Inactive
Classifier: Environment :: Web Environment
Classifier: Intended Audience :: Developers
Classifier: License :: OSI Approved :: Zope Public License
Classifier: Programming Language :: Python
Classifier: Programming Language :: Python :: 3
Classifier: Programming Language :: Python :: 3.7
Classifier: Programming Language :: Python :: 3.8
Classifier: Programming Language :: Python :: 3.9
Classifier: Programming Language :: Python :: 3.10
Classifier: Programming Language :: Python :: 3.11
Classifier: Programming Language :: Python :: Implementation
Classifier: Programming Language :: Python :: Implementation :: CPython
Classifier: Programming Language :: Python :: Implementation :: PyPy
Classifier: Framework :: Zope :: 3
Requires-Python: >= 3.7
Requires-Dist: grokcore.component (>=2.5dev)
Requires-Dist: grokcore.security
Requires-Dist: grokcore.traverser (>=3.0.0)
Requires-Dist: grokcore.view
Requires-Dist: martian
Requires-Dist: setuptools
Requires-Dist: zope.component
Requires-Dist: zope.interface
Requires-Dist: zope.publisher (>=4.2.2)
Provides-Extra: test
Requires-Dist: grokcore.content ; extra == 'test'
Requires-Dist: grokcore.view[security_publication] ; extra == 'test'
Requires-Dist: grokcore.view[test] ; extra == 'test'
Requires-Dist: zope.app.appsetup ; extra == 'test'
Requires-Dist: zope.app.wsgi[test] ; extra == 'test'
Requires-Dist: zope.errorview (>=1.2) ; extra == 'test'
Requires-Dist: zope.testbrowser ; extra == 'test'
Requires-Dist: zope.testing ; extra == 'test'
